roboactions/__init__.py
roboactions/_version.py
roboactions/config.py
roboactions/exceptions.py
roboactions/http.py
roboactions/policy.py
roboactions/remote_env.py
roboactions/remotegym.py
roboactions/serialize.py
roboactions/resources/__init__.py
roboactions-0.1.2.dist-info/licenses/LICENSE
roboactions-0.1.2.dist-info/METADATA
roboactions-0.1.2.dist-info/WHEEL
roboactions-0.1.2.dist-info/top_level.txt
roboactions-0.1.2.dist-info/RECORD
