Metadata-Version: 2.4
Name: roboactions
Version: 0.1.2
Summary: Python client SDK for the RoboActions automation platform.
Author-email: RoboActions <eishan@roboactions.com>
License: 
Project-URL: Homepage, https://www.roboactions.com
Project-URL: Documentation, https://docs.roboactions.com/sdk/python
Project-URL: Repository, https://github.com/RoboActions/RoboActions
Project-URL: Issues, https://github.com/RoboActions/RoboActions/issues
Keywords: automation,workflow,sdk,client,roboactions
Classifier: Development Status :: 3 - Alpha
Classifier: Intended Audience :: Developers
Classifier: License :: OSI Approved :: Apache Software License
Classifier: Operating System :: OS Independent
Classifier: Programming Language :: Python
Classifier: Programming Language :: Python :: 3
Classifier: Programming Language :: Python :: 3 :: Only
Classifier: Programming Language :: Python :: 3.9
Classifier: Programming Language :: Python :: 3.10
Classifier: Programming Language :: Python :: 3.11
Classifier: Programming Language :: Python :: 3.12
Classifier: Topic :: Software Development :: Libraries :: Python Modules
Requires-Python: >=3.9
License-File: LICENSE
Requires-Dist: requests>=2.32.3
Requires-Dist: pydantic>=2.8.2
Requires-Dist: msgpack>=1.0.0
Requires-Dist: numpy>=1.24.0
Requires-Dist: torch
Requires-Dist: websocket-client>=1.8.0
Requires-Dist: gymnasium>=0.29.0
Requires-Dist: gymnasium[other]
Requires-Dist: Pillow>=10.0.0
Provides-Extra: dev
Requires-Dist: pytest>=8.1; extra == "dev"
Requires-Dist: pytest-cov>=5.0; extra == "dev"
Requires-Dist: ruff>=0.6; extra == "dev"
Requires-Dist: mypy>=1.10; extra == "dev"
Dynamic: license-file
